exasol/saas/client/__init__.py
exasol/saas/client/api_access.py
exasol/saas/client/openapi/__init__.py
exasol/saas/client/openapi/api/__init__.py
exasol/saas/client/openapi/api/clusters/__init__.py
exasol/saas/client/openapi/api/clusters/create_cluster.py
exasol/saas/client/openapi/api/clusters/delete_cluster.py
exasol/saas/client/openapi/api/clusters/get_cluster.py
exasol/saas/client/openapi/api/clusters/get_cluster_connection.py
exasol/saas/client/openapi/api/clusters/list_clusters.py
exasol/saas/client/openapi/api/clusters/scale_cluster.py
exasol/saas/client/openapi/api/clusters/start_cluster.py
exasol/saas/client/openapi/api/clusters/stop_cluster.py
exasol/saas/client/openapi/api/clusters/update_cluster.py
exasol/saas/client/openapi/api/databases/__init__.py
exasol/saas/client/openapi/api/databases/create_database.py
exasol/saas/client/openapi/api/databases/create_schedule.py
exasol/saas/client/openapi/api/databases/delete_database.py
exasol/saas/client/openapi/api/databases/delete_schedule.py
exasol/saas/client/openapi/api/databases/dlhc_activate.py
exasol/saas/client/openapi/api/databases/get_database.py
exasol/saas/client/openapi/api/databases/get_database_settings.py
exasol/saas/client/openapi/api/databases/get_database_upgrade_info.py
exasol/saas/client/openapi/api/databases/get_dlhc_activate_status.py
exasol/saas/client/openapi/api/databases/list_databases.py
exasol/saas/client/openapi/api/databases/list_schedules.py
exasol/saas/client/openapi/api/databases/set_auto_updates_database.py
exasol/saas/client/openapi/api/databases/start_database.py
exasol/saas/client/openapi/api/databases/stop_database.py
exasol/saas/client/openapi/api/databases/update_database.py
exasol/saas/client/openapi/api/databases/upgrade_database.py
exasol/saas/client/openapi/api/extensions/__init__.py
exasol/saas/client/openapi/api/extensions/create_extension_instance.py
exasol/saas/client/openapi/api/extensions/delete_extension_instance.py
exasol_saas_api-2.3.0.dist-info/LICENSE
exasol_saas_api-2.3.0.dist-info/METADATA
exasol_saas_api-2.3.0.dist-info/WHEEL
exasol_saas_api-2.3.0.dist-info/entry_points.txt
exasol_saas_api-2.3.0.dist-info/RECORD
